{
  "generated_at": "2026-03-02T22:45:36.692288Z",
  "headline": {
    "title": "US jets shot down over Kuwait in 'apparent friendly fire incident', officials say",
    "url": "https://www.bbc.com/news/articles/c5y4v8gndz1o?at_medium=RSS&at_campaign=rss"
  },
  "sections": [
    {
      "title": "CHUDS VS SHITLIBS",
      "items": [
        {
          "title": "US jets shot down over Kuwait in 'apparent friendly fire incident', officials say",
          "url": "https://www.bbc.com/news/articles/c5y4v8gndz1o?at_medium=RSS&at_campaign=rss",
          "source": "BBC News",
          "ts": "Mon, 02 Mar 2026 17:37:27 GMT"
        },
        {
          "title": "Hopes and fears as US Iranians take to streets after toppling of supreme leader",
          "url": "https://www.bbc.com/news/articles/cy4w728kl4ko?at_medium=RSS&at_campaign=rss",
          "source": "BBC News",
          "ts": "Mon, 02 Mar 2026 02:59:25 GMT"
        },
        {
          "title": "Why did US and Israel attack Iran and how long could the war last?",
          "url": "https://www.bbc.com/news/articles/cx2dyz6p3weo?at_medium=RSS&at_campaign=rss",
          "source": "BBC News",
          "ts": "Mon, 02 Mar 2026 21:36:19 GMT"
        },
        {
          "title": "Texas Senate candidates' final push ahead of Tuesday primaries",
          "url": "https://www.npr.org/2026/03/02/nx-s1-5727594/texas-senate-candidates-final-push-ahead-of-tuesday-primaries",
          "source": "NPR Topics: Politics",
          "ts": "Mon, 02 Mar 2026 16:52:21 -0500"
        },
        {
          "title": "Video of Clinton depositions in Epstein investigation released by House Republicans",
          "url": "https://www.npr.org/2026/03/02/nx-s1-5732871/bill-clinton-hillary-clinton-depositions-epstein-files",
          "source": "NPR Topics: Politics",
          "ts": "Mon, 02 Mar 2026 16:29:15 -0500"
        },
        {
          "title": "Ivermectin is making a post-pandemic comeback, among cancer patients",
          "url": "https://www.npr.org/2026/03/02/nx-s1-5729102/ivermectin-politics-treatment-cancer-evidence",
          "source": "NPR Topics: Politics",
          "ts": "Mon, 02 Mar 2026 07:00:00 -0500"
        },
        {
          "title": "They’re Hiring at U.S.A.I.D. Just Not Anyone Who Worked There.",
          "url": "https://www.nytimes.com/2026/03/02/us/politics/usaid-hiring.html",
          "source": "NYT > U.S. > Politics",
          "ts": "Mon, 02 Mar 2026 22:36:18 +0000"
        },
        {
          "title": "President Trump Appears at Public Event With a Red Skin Rash",
          "url": "https://www.nytimes.com/2026/03/02/us/politics/trump-rash-neck.html",
          "source": "NYT > U.S. > Politics",
          "ts": "Mon, 02 Mar 2026 22:32:51 +0000"
        },
        {
          "title": "As Maduro and Khamenei Learned, It’s Harder Than Ever for Leaders to Hide",
          "url": "https://www.nytimes.com/2026/03/02/us/politics/maduro-khamenei-trump-surveillance.html",
          "source": "NYT > U.S. > Politics",
          "ts": "Mon, 02 Mar 2026 22:27:24 +0000"
        },
        {
          "title": "White House says Trump's red neck rash was caused by prescription skin cream",
          "url": "https://www.washingtontimes.com/news/2026/mar/2/white-house-says-trumps-red-neck-rash-caused-prescription-skin-cream/",
          "source": "The Washington Times stories: Politics",
          "ts": "Mon, 02 Mar 2026 16:09:24 -0500"
        },
        {
          "title": "Embattled Sen. Susan Collins goes back to roots to remind voters of her clout",
          "url": "https://www.washingtontimes.com/news/2026/mar/2/susan-collins-goes-back-roots-remind-voters-clout/",
          "source": "The Washington Times stories: Politics",
          "ts": "Mon, 02 Mar 2026 15:52:38 -0500"
        },
        {
          "title": "Court ruling lets members of Congress inspect ICE facilities",
          "url": "https://www.washingtontimes.com/news/2026/mar/2/court-ruling-lets-members-congress-inspect-ice-facilities/",
          "source": "The Washington Times stories: Politics",
          "ts": "Mon, 02 Mar 2026 14:18:53 -0500"
        },
        {
          "title": "Hegseth Lays Out 3-Part Mission: Conflict 'Not Endless'",
          "url": "https://www.realclearpolitics.com/2026/03/02/hegseth_lays_out_3-part_mission_conflict_not_endless_693321.html",
          "source": "RealClearPolitics - Homepage",
          "ts": "Mon, 02 Mar 2026 13:47:30 -0600"
        },
        {
          "title": "Is Iran the World's Most Inexplicable Country?",
          "url": "https://www.realclearpolitics.com/2026/03/02/is_iran_the_worlds_most_inexplicable_country_693289.html",
          "source": "RealClearPolitics - Homepage",
          "ts": "Mon, 02 Mar 2026 13:47:33 -0600"
        },
        {
          "title": "Who Takes Over Iran? How Does the Regime Get Changed?",
          "url": "https://www.realclearpolitics.com/video/2026/03/01/erik_prince_on_iran_who_takes_over_how_does_the_regime_get_changed.html",
          "source": "RealClearPolitics - Homepage",
          "ts": "Mon, 02 Mar 2026 13:47:40 -0600"
        },
        {
          "title": "Make up artist Alexis Stone claims to be Jim Carrey imposter after clone conspiracy",
          "url": "https://www.thepinknews.com/2026/03/02/make-up-artist-alexis-stone-claims-to-be-jim-carrey-imposter-after-clone-conspiracy/",
          "source": "PinkNews | Latest lesbian, gay, bi and trans news | LGBTQ+ news",
          "ts": "Mon, 02 Mar 2026 14:33:33 +0000"
        },
        {
          "title": "Scream 7 star Anna Camp apologises for sharing post about film’s boycott",
          "url": "https://www.thepinknews.com/2026/03/02/scream-7-anna-camp-boycott-apology/",
          "source": "PinkNews | Latest lesbian, gay, bi and trans news | LGBTQ+ news",
          "ts": "Mon, 02 Mar 2026 13:07:07 +0000"
        },
        {
          "title": "Bridgerton boss calls Benedict’s bisexual coming out a ‘beautiful moment’",
          "url": "https://www.thepinknews.com/2026/03/02/bridgerton-boss-calls-benedicts-bisexual-coming-out-a-beautiful-moment/",
          "source": "PinkNews | Latest lesbian, gay, bi and trans news | LGBTQ+ news",
          "ts": "Mon, 02 Mar 2026 12:17:36 +0000"
        }
      ]
    },
    {
      "title": "CULTURE WAR",
      "items": [
        {
          "title": "Why A War With Iran Means Confronting Radical Evil",
          "url": "https://religionnews.com/2026/03/02/a-war-with-iran-means-confronting-radical-evil/",
          "source": "RNS",
          "ts": "Mon, 02 Mar 2026 21:28:01 +0000"
        },
        {
          "title": "Impulsive kings and random chance: Purim’s parallels to our political moment",
          "url": "https://religionnews.com/2026/03/02/impulsive-kings-and-random-chance-purims-parallels-to-our-political-moment/",
          "source": "RNS",
          "ts": "Mon, 02 Mar 2026 20:30:39 +0000"
        },
        {
          "title": "Hundreds of corrections being issued for Texas’ Bible-infused curriculum",
          "url": "https://religionnews.com/2026/03/02/hundreds-of-corrections-being-issued-for-texas-bible-infused-curriculum/",
          "source": "RNS",
          "ts": "Mon, 02 Mar 2026 19:06:06 +0000"
        },
        {
          "title": "On the Chagos Islands, Trump Is Right",
          "url": "https://www.theatlantic.com/ideas/2026/03/chagos-islands-trump-britain-mauritius/686214/?utm_source=feed",
          "source": "The Atlantic",
          "ts": "2026-03-02T17:07:00-05:00"
        },
        {
          "title": "The Big Story: The Iran War",
          "url": "https://www.theatlantic.com/national-security/2026/03/big-story-iran-war/686211/?utm_source=feed",
          "source": "The Atlantic",
          "ts": "2026-03-02T16:39:00-05:00"
        },
        {
          "title": "Today’s <em>Atlantic</em> Trivia: Crack Open a Krating Daeng",
          "url": "https://www.theatlantic.com/newsletters/2026/03/daily-trivia-questions-answers-week-19/686213/?utm_source=feed",
          "source": "The Atlantic",
          "ts": "2026-03-02T16:35:20-05:00"
        },
        {
          "title": "The civilians dying in Trump’s new war",
          "url": "https://www.vox.com/politics/481245/us-israel-iran-war-civilian-death-toll-school-strike",
          "source": "Vox",
          "ts": "2026-03-02T17:15:00-05:00"
        },
        {
          "title": "The Supreme Court appears likely to let stoners own guns",
          "url": "https://www.vox.com/policy/481254/supreme-court-hemani-marijuana-guns-second-amendment",
          "source": "Vox",
          "ts": "2026-03-02T14:35:00-05:00"
        },
        {
          "title": "The “Epstein class,” explained",
          "url": "https://www.vox.com/podcasts/480850/epstein-files-ro-khanna-accountability-congress-explained",
          "source": "Vox",
          "ts": "2026-03-02T07:00:00-05:00"
        },
        {
          "title": "Republican Ryan Zinke to step down as US congressman",
          "url": "https://www.theguardian.com/us-news/2026/mar/02/ryan-zinke-montana-us-house",
          "source": "US news | The Guardian",
          "ts": "Mon, 02 Mar 2026 22:19:57 GMT"
        },
        {
          "title": "Ron DeSantis spent $1.2m per day to open and operate ‘Alligator Alcatraz’",
          "url": "https://www.theguardian.com/us-news/2026/mar/02/ron-desantis-12-million-on-alligator-alcatraz",
          "source": "US news | The Guardian",
          "ts": "Mon, 02 Mar 2026 22:10:25 GMT"
        },
        {
          "title": "US House committee releases videos of the Clintons’ Epstein testimonies",
          "url": "https://www.theguardian.com/us-news/2026/mar/02/clintons-epstein-testimony-released",
          "source": "US news | The Guardian",
          "ts": "Mon, 02 Mar 2026 21:38:53 GMT"
        }
      ]
    },
    {
      "title": "MILITARY INDUSTRIAL COMPLEX",
      "items": []
    },
    {
      "title": "PARA POLITICAL INTRIGUE",
      "items": []
    }
  ]
}