{
  "generated_at": "2025-12-25T15:30:32.167820Z",
  "headline": {
    "title": "Officials discover a million more documents potentially related to Epstein case",
    "url": "https://www.bbc.com/news/articles/czdgz84dn35o?at_medium=RSS&at_campaign=rss"
  },
  "sections": [
    {
      "title": "CHUDS VS SHITLIBS",
      "items": [
        {
          "title": "Officials discover a million more documents potentially related to Epstein case",
          "url": "https://www.bbc.com/news/articles/czdgz84dn35o?at_medium=RSS&at_campaign=rss",
          "source": "BBC News",
          "ts": "Wed, 24 Dec 2025 22:55:25 GMT"
        },
        {
          "title": "Venezuela accuses US of 'extortion' over seizure of oil tankers",
          "url": "https://www.bbc.com/news/articles/cd749gqgg11o?at_medium=RSS&at_campaign=rss",
          "source": "BBC News",
          "ts": "Wed, 24 Dec 2025 09:46:14 GMT"
        },
        {
          "title": "Where is Santa now? Trump answers kids' Christmas calls to Norad tracker",
          "url": "https://www.bbc.com/news/videos/cqxqvd0z5gno?at_medium=RSS&at_campaign=rss",
          "source": "BBC News",
          "ts": "Thu, 25 Dec 2025 00:41:15 GMT"
        },
        {
          "title": "For Trump, 'America First' has meant an aggressive use of power in foreign policy",
          "url": "https://www.npr.org/2025/12/25/nx-s1-5647706/for-trump-america-first-has-meant-an-aggressive-use-of-power-in-foreign-policy",
          "source": "NPR Topics: Politics",
          "ts": "Thu, 25 Dec 2025 06:52:51 -0500"
        },
        {
          "title": "Former ambassador talks about Trump's foreign policy approach during his second term",
          "url": "https://www.npr.org/2025/12/25/nx-s1-5649762/former-ambassador-talks-about-trumps-foreign-policy-approach-during-his-second-term",
          "source": "NPR Topics: Politics",
          "ts": "Thu, 25 Dec 2025 06:52:40 -0500"
        },
        {
          "title": "How one politically divided family keeps the peace during the holidays",
          "url": "https://www.npr.org/2025/12/25/nx-s1-5647745/how-one-politically-divided-family-keeps-the-peace-during-the-holidays",
          "source": "NPR Topics: Politics",
          "ts": "Thu, 25 Dec 2025 04:58:25 -0500"
        },
        {
          "title": "With Trump in Power, Democrats Try to Redefine Themselves as Disrupters",
          "url": "https://www.nytimes.com/2025/12/25/us/politics/trump-democrats-washington-midterm-elections.html",
          "source": "NYT > U.S. > Politics",
          "ts": "Thu, 25 Dec 2025 10:01:55 +0000"
        },
        {
          "title": "Republicans Who Backed Afghan Visas Are Mum as Trump Halts Them",
          "url": "https://www.nytimes.com/2025/12/25/us/politics/republicans-afghan-visas.html",
          "source": "NYT > U.S. > Politics",
          "ts": "Thu, 25 Dec 2025 10:01:00 +0000"
        },
        {
          "title": "Palau Agrees to Take Up to 75 Migrants From the U.S.",
          "url": "https://www.nytimes.com/2025/12/24/us/politics/palau-us-migrants.html",
          "source": "NYT > U.S. > Politics",
          "ts": "Wed, 24 Dec 2025 21:27:54 +0000"
        },
        {
          "title": "House Republicans close out 2025 touting a long list of legislative wins",
          "url": "https://www.washingtontimes.com/news/2025/dec/25/house-republicans-close-2025-touting-long-list-legislative-wins/",
          "source": "The Washington Times stories: Politics",
          "ts": "Thu, 25 Dec 2025 09:11:44 -0500"
        },
        {
          "title": "Rep. Sheri Biggs urges VA to offer faith-based mental health care",
          "url": "https://www.washingtontimes.com/news/2025/dec/25/rep-sheri-biggs-urges-va-offer-faith-based-mental-health-care/",
          "source": "The Washington Times stories: Politics",
          "ts": "Thu, 25 Dec 2025 09:03:05 -0500"
        },
        {
          "title": "Trump-backed candidate Nasry Asfura declared winner of Honduras' presidential vote",
          "url": "https://www.washingtontimes.com/news/2025/dec/24/trump-backed-candidate-declared-winner-honduras-presidential-vote/",
          "source": "The Washington Times stories: Politics",
          "ts": "Wed, 24 Dec 2025 16:52:47 -0500"
        },
        {
          "title": "O Holy Night",
          "url": "https://www.realclearpolitics.com/2025/12/24/o_holy_night_681444.html",
          "source": "RealClearPolitics - Homepage",
          "ts": "Wed, 24 Dec 2025 08:20:22 -0600"
        },
        {
          "title": "At Christmas, God Fulfills His Purpose - and Gives Us Ours",
          "url": "https://www.realclearpolitics.com/2025/12/24/at_christmas_god_fulfills_his_purpose_-_and_gives_us_ours_681443.html",
          "source": "RealClearPolitics - Homepage",
          "ts": "Wed, 24 Dec 2025 08:34:56 -0600"
        },
        {
          "title": "The Demise of Religion Among Democrats",
          "url": "https://www.realclearpolitics.com/2025/12/24/the_demise_of_religion_among_democrats_681466.html",
          "source": "RealClearPolitics - Homepage",
          "ts": "Wed, 24 Dec 2025 08:10:17 -0600"
        },
        {
          "title": "How Illegal Immigration, Government Failure Fuel Identity Theft",
          "url": "https://www.realclearinvestigations.com/articles/2025/12/24/how_illegal_immigration_and_government_failure_fuel_identity_theft_1155167.html",
          "source": "RealClearPolitics - Homepage",
          "ts": "Wed, 24 Dec 2025 08:17:50 -0600"
        },
        {
          "title": "25 best queer shows of 2025 ranked, from Stranger Things to Heated Rivalry",
          "url": "https://www.thepinknews.com/2025/12/25/best-queer-tv-shows-of-2025-ranked/",
          "source": "PinkNews | Latest lesbian, gay, bi and trans news | LGBTQ+ news",
          "ts": "Thu, 25 Dec 2025 12:00:00 +0000"
        },
        {
          "title": "27 versions of ‘White Christmas’ ranked, from Lady Gaga to Taylor Swift",
          "url": "https://www.thepinknews.com/2025/12/25/27-versions-of-white-christmas-ranked-lady-gaga-taylor-swift-bing-crosby/",
          "source": "PinkNews | Latest lesbian, gay, bi and trans news | LGBTQ+ news",
          "ts": "Thu, 25 Dec 2025 10:00:00 +0000"
        },
        {
          "title": "BBC ‘apologises’ to ex-presenter for ‘homophobic abuse’",
          "url": "https://www.thepinknews.com/2025/12/24/bbc-jack-murley-homophobia-apology/",
          "source": "PinkNews | Latest lesbian, gay, bi and trans news | LGBTQ+ news",
          "ts": "Wed, 24 Dec 2025 14:33:46 +0000"
        }
      ]
    },
    {
      "title": "CULTURE WAR",
      "items": [
        {
          "title": "Recognizing a Palestinian state isn’t an antisemitic act",
          "url": "https://religionnews.com/2025/12/24/recognizing-a-palestinian-state-isnt-an-antisemitic-act/",
          "source": "RNS",
          "ts": "Wed, 24 Dec 2025 19:40:57 +0000"
        },
        {
          "title": "US Jewish organizations call on Trump to rescind travel ban on Palestinians",
          "url": "https://religionnews.com/2025/12/24/us-jewish-organizations-call-on-trump-to-rescind-travel-ban-on-palestinians/",
          "source": "RNS",
          "ts": "Wed, 24 Dec 2025 19:40:03 +0000"
        },
        {
          "title": "Keep Christ in Christmas? First, keep Christ in Christian",
          "url": "https://religionnews.com/2025/12/24/keep-christ-in-christmas-its-not-about-your-holiday-themed-caramel-macchiato-cup/",
          "source": "RNS",
          "ts": "Wed, 24 Dec 2025 19:29:27 +0000"
        },
        {
          "title": "Watching Someone Fail Shouldn’t Be So Fun",
          "url": "https://www.theatlantic.com/culture/2025/12/marty-supreme-review-timothee-chalamet/685462/?utm_source=feed",
          "source": "The Atlantic",
          "ts": "2025-12-25T08:00:00-05:00"
        },
        {
          "title": "Is Victor Wembanyama Too Tall?",
          "url": "https://www.theatlantic.com/technology/2025/12/victor-wembanyama-freak-athletes/685449/?utm_source=feed",
          "source": "The Atlantic",
          "ts": "2025-12-25T08:00:00-05:00"
        },
        {
          "title": "Netflix vs. Paramount",
          "url": "https://www.theatlantic.com/podcasts/2025/12/warner-brothers-discovery-netflix-paramount-trump/685386/?utm_source=feed",
          "source": "The Atlantic",
          "ts": "2025-12-25T08:00:00-05:00"
        },
        {
          "title": "The 12 Days of Christmas: The story behind the holiday’s most annoying carol",
          "url": "https://www.vox.com/21796404/12-days-of-christmas-explained",
          "source": "Vox",
          "ts": "2025-12-25T08:21:07-05:00"
        },
        {
          "title": "The eternal awkwardness of winter break",
          "url": "https://www.vox.com/life/392230/winter-break-holidays-new-year-kids-vacation",
          "source": "Vox",
          "ts": "2025-12-25T08:20:45-05:00"
        },
        {
          "title": "JD Vance and the future of MAGA",
          "url": "https://www.vox.com/podcasts/473022/jd-vance-explained-ian-ward",
          "source": "Vox",
          "ts": "2025-12-25T07:00:00-05:00"
        },
        {
          "title": "Arkansas Powerball lottery player wins $1.817bn jackpot on Christmas Eve",
          "url": "https://www.theguardian.com/us-news/2025/dec/25/arkansas-powerball-christmas-eve",
          "source": "US news | The Guardian",
          "ts": "Thu, 25 Dec 2025 14:20:30 GMT"
        },
        {
          "title": "How effective is protesting? According to historians and political scientists: very",
          "url": "https://www.theguardian.com/us-news/2025/dec/25/protests-effective-history-impact",
          "source": "US news | The Guardian",
          "ts": "Thu, 25 Dec 2025 14:00:42 GMT"
        },
        {
          "title": "Her partner was detained. Now she and their baby face Christmas without him: ‘My family is broken’",
          "url": "https://www.theguardian.com/us-news/2025/dec/25/immigration-san-francisco-christmas-separation",
          "source": "US news | The Guardian",
          "ts": "Thu, 25 Dec 2025 12:00:42 GMT"
        }
      ]
    },
    {
      "title": "MILITARY INDUSTRIAL COMPLEX",
      "items": []
    },
    {
      "title": "PARA POLITICAL INTRIGUE",
      "items": []
    }
  ]
}